{
  "title": "Deployment Overview",
  "description": "Track deployments, rollouts, and service health during deploys",
  "tags": ["deployment", "devctl", "operations"],
  "timezone": "browser",
  "editable": true,
  "fiscalYearStartMonth": 0,
  "graphTooltip": 1,
  "panels": [
    {
      "id": 1,
      "title": "Deployment Annotations",
      "type": "timeseries",
      "gridPos": {"h": 8, "w": 24, "x": 0, "y": 0},
      "targets": [
        {
          "refId": "A",
          "expr": "sum(rate(http_requests_total[5m])) by (service)",
          "legendFormat": "{{service}}"
        }
      ],
      "options": {
        "legend": {"displayMode": "table", "placement": "right"}
      },
      "fieldConfig": {
        "defaults": {
          "custom": {
            "drawStyle": "line",
            "lineWidth": 1,
            "fillOpacity": 10
          }
        }
      }
    },
    {
      "id": 2,
      "title": "Error Rate",
      "type": "timeseries",
      "gridPos": {"h": 8, "w": 12, "x": 0, "y": 8},
      "targets": [
        {
          "refId": "A",
          "expr": "sum(rate(http_requests_total{status=~\"5..\"}[5m])) / sum(rate(http_requests_total[5m])) * 100",
          "legendFormat": "Error Rate %"
        }
      ],
      "fieldConfig": {
        "defaults": {
          "unit": "percent",
          "thresholds": {
            "mode": "absolute",
            "steps": [
              {"color": "green", "value": null},
              {"color": "yellow", "value": 1},
              {"color": "red", "value": 5}
            ]
          }
        }
      }
    },
    {
      "id": 3,
      "title": "Response Time p99",
      "type": "timeseries",
      "gridPos": {"h": 8, "w": 12, "x": 12, "y": 8},
      "targets": [
        {
          "refId": "A",
          "expr": "histogram_quantile(0.99, sum(rate(http_request_duration_seconds_bucket[5m])) by (le, service))",
          "legendFormat": "{{service}} p99"
        }
      ],
      "fieldConfig": {
        "defaults": {
          "unit": "s",
          "thresholds": {
            "mode": "absolute",
            "steps": [
              {"color": "green", "value": null},
              {"color": "yellow", "value": 0.5},
              {"color": "red", "value": 1}
            ]
          }
        }
      }
    },
    {
      "id": 4,
      "title": "Pod Status",
      "type": "stat",
      "gridPos": {"h": 4, "w": 6, "x": 0, "y": 16},
      "targets": [
        {
          "refId": "A",
          "expr": "sum(kube_pod_status_ready{condition=\"true\"})",
          "legendFormat": "Ready"
        }
      ],
      "options": {
        "colorMode": "value",
        "graphMode": "none"
      }
    },
    {
      "id": 5,
      "title": "Pods Not Ready",
      "type": "stat",
      "gridPos": {"h": 4, "w": 6, "x": 6, "y": 16},
      "targets": [
        {
          "refId": "A",
          "expr": "sum(kube_pod_status_ready{condition=\"false\"})",
          "legendFormat": "Not Ready"
        }
      ],
      "options": {
        "colorMode": "value",
        "graphMode": "none"
      },
      "fieldConfig": {
        "defaults": {
          "thresholds": {
            "mode": "absolute",
            "steps": [
              {"color": "green", "value": null},
              {"color": "yellow", "value": 1},
              {"color": "red", "value": 3}
            ]
          }
        }
      }
    },
    {
      "id": 6,
      "title": "Container Restarts",
      "type": "stat",
      "gridPos": {"h": 4, "w": 6, "x": 12, "y": 16},
      "targets": [
        {
          "refId": "A",
          "expr": "sum(increase(kube_pod_container_status_restarts_total[1h]))",
          "legendFormat": "Restarts (1h)"
        }
      ],
      "options": {
        "colorMode": "value",
        "graphMode": "area"
      },
      "fieldConfig": {
        "defaults": {
          "thresholds": {
            "mode": "absolute",
            "steps": [
              {"color": "green", "value": null},
              {"color": "yellow", "value": 5},
              {"color": "red", "value": 10}
            ]
          }
        }
      }
    },
    {
      "id": 7,
      "title": "Deployment Revision",
      "type": "stat",
      "gridPos": {"h": 4, "w": 6, "x": 18, "y": 16},
      "targets": [
        {
          "refId": "A",
          "expr": "max(kube_deployment_status_observed_generation) by (deployment)",
          "legendFormat": "{{deployment}}"
        }
      ]
    },
    {
      "id": 8,
      "title": "Recent Deployments",
      "type": "table",
      "gridPos": {"h": 8, "w": 24, "x": 0, "y": 20},
      "targets": [
        {
          "refId": "A",
          "expr": "changes(kube_deployment_status_observed_generation[24h]) > 0",
          "format": "table",
          "instant": true
        }
      ],
      "options": {
        "showHeader": true
      },
      "transformations": [
        {
          "id": "organize",
          "options": {
            "excludeByName": {"Time": true, "__name__": true}
          }
        }
      ]
    }
  ],
  "annotations": {
    "list": [
      {
        "datasource": "-- Grafana --",
        "enable": true,
        "hide": false,
        "iconColor": "rgba(0, 211, 255, 1)",
        "name": "Deployments",
        "type": "tags",
        "tags": ["deployment"]
      }
    ]
  },
  "templating": {
    "list": [
      {
        "name": "namespace",
        "type": "query",
        "query": "label_values(kube_pod_info, namespace)",
        "refresh": 1,
        "multi": true,
        "includeAll": true
      },
      {
        "name": "service",
        "type": "query",
        "query": "label_values(kube_deployment_labels, deployment)",
        "refresh": 1,
        "multi": true,
        "includeAll": true
      }
    ]
  },
  "time": {"from": "now-6h", "to": "now"},
  "refresh": "30s"
}
